lamed/VERSION
lamed/__init__.py
lamed/aws_api.py
lamed/cli.py
lamed/config.json.template
lamed/config.py
lamed/deploy.py
lamed/lamed.py
lamed/logger.py
lamed/vendor/redis/__init__.py
lamed/vendor/redis/_compat.py
lamed/vendor/redis/client.py
lamed/vendor/redis/connection.py
lamed/vendor/redis/exceptions.py
lamed/vendor/redis/lock.py
lamed/vendor/redis/sentinel.py
lamed/vendor/redis/utils.py
lamed/vendor/redis/__pycache__/__init__.cpython-38.pyc
lamed/vendor/redis/__pycache__/_compat.cpython-38.pyc
lamed/vendor/redis/__pycache__/client.cpython-38.pyc
lamed/vendor/redis/__pycache__/connection.cpython-38.pyc
lamed/vendor/redis/__pycache__/exceptions.cpython-38.pyc
lamed/vendor/redis/__pycache__/lock.cpython-38.pyc
lamed/vendor/redis/__pycache__/sentinel.cpython-38.pyc
lamed/vendor/redis/__pycache__/utils.cpython-38.pyc
lamed-0.4.3.dist-info/LICENSE
lamed-0.4.3.dist-info/METADATA
lamed-0.4.3.dist-info/WHEEL
lamed-0.4.3.dist-info/entry_points.txt
lamed-0.4.3.dist-info/top_level.txt
lamed/vendor/redis-3.4.1.dist-info/INSTALLER
lamed/vendor/redis-3.4.1.dist-info/LICENSE
lamed/vendor/redis-3.4.1.dist-info/METADATA
lamed/vendor/redis-3.4.1.dist-info/RECORD
lamed/vendor/redis-3.4.1.dist-info/WHEEL
lamed/vendor/redis-3.4.1.dist-info/top_level.txt
lamed-0.4.3.dist-info/RECORD
