Metadata-Version: 2.1
Name: lamed
Version: 0.4.3
Summary: Run your own A/B testing backend on AWS Lambda
Home-page: https://github.com/Alephbet/lamed
Author: Yoav Aner
Author-email: yoav@gingerlime.com
License: UNKNOWN
Platform: UNKNOWN
Classifier: Development Status :: 5 - Production/Stable
Classifier: Intended Audience :: Developers
Classifier: Intended Audience :: System Administrators
Classifier: Natural Language :: English
Classifier: License :: OSI Approved :: MIT License
Classifier: Programming Language :: Python
Classifier: Programming Language :: Python :: 2.7
Classifier: Programming Language :: Python :: 3
Classifier: Programming Language :: Python :: 3.3
Classifier: Programming Language :: Python :: 3.4
Classifier: Programming Language :: Python :: 3.5
Classifier: Programming Language :: Python :: 3.6
Classifier: Programming Language :: Python :: 3.7
Requires-Dist: awscli (>=1.18.36)
Requires-Dist: jmespath (>=0.9.5)
Requires-Dist: boto3 (>=1.12.36)
Requires-Dist: click (>=7.1.1)
Requires-Dist: redis (>=3.4.1)
